evalbase/__init__.py
evalbase/decorators.py
evalbase/telemetry.py
evalbase-0.0.2.dist-info/licenses/LICENSE
evalbase-0.0.2.dist-info/METADATA
evalbase-0.0.2.dist-info/WHEEL
evalbase-0.0.2.dist-info/top_level.txt
evalbase-0.0.2.dist-info/RECORD
