Metadata-Version: 2.4
Name: evalbase
Version: 0.0.2
Summary: Evalbase SDK for AI workflow telemetry using OpenTelemetry
Author-email: Zach Smith <zach@evalbase.ai>
License:                                  Apache License
Project-URL: homepage, https://github.com/evalbase/evalbase-python-sdk
Project-URL: repository, https://github.com/evalbase/evalbase-python-sdk
Requires-Python: >=3.8
License-File: LICENSE
Requires-Dist: opentelemetry-api
Requires-Dist: opentelemetry-sdk
Requires-Dist: opentelemetry-exporter-otlp-proto-http
Provides-Extra: test
Requires-Dist: pytest; extra == "test"
Requires-Dist: pytest-asyncio; extra == "test"
Dynamic: license-file
